CHANGELOG.rst
MANIFEST.in
README.rst
dist_utils.py
requirements.txt
setup.cfg
setup.py
bwc_cli/__init__.py
bwc_cli/shell.py
bwc_cli.egg-info/PKG-INFO
bwc_cli.egg-info/SOURCES.txt
bwc_cli.egg-info/dependency_links.txt
bwc_cli.egg-info/entry_points.txt
bwc_cli.egg-info/namespace_packages.txt
bwc_cli.egg-info/not-zip-safe
bwc_cli.egg-info/requires.txt
bwc_cli.egg-info/top_level.txt
bwc_cli/common/__init__.py
bwc_cli/common/command.py
bwc_cli/common/commandmanager.py
bwc_cli/common/resource.py
bwc_cli/ipf/__init__.py
bwc_cli/ipf/fabric.py
bwc_cli/ipf/firmware.py
bwc_cli/ipf/inventory.py
bwc_cli/ipf/show.py
bwc_cli/ipf/workflow.py