Metadata-Version: 1.1
Name: bwc-cli
Version: 2.1.0
Summary: Brocade Workflow Composer CLI
Home-page: https://github.com/StackStorm/bwc-cli
Author: Brocade
Author-email: support@brocade.com
License: UNKNOWN
Keywords: workflow,composer,cli,stackstorm
Platform: UNKNOWN
Classifier: Development Status :: 5 - Production/Stable
Classifier: Intended Audience :: Information Technology
Classifier: Intended Audience :: Developers
Classifier: Intended Audience :: System Administrators
Classifier: License :: Other/Proprietary License
Classifier: Operating System :: POSIX :: Linux
Classifier: Programming Language :: Python
Classifier: Programming Language :: Python :: 2
Classifier: Programming Language :: Python :: 2.7
